{"docs":[{"fields":[{"collapsible":0,"no_copy":0,"creation":"2017-02-02 11:00:24.853005","search_fields":["patient_name","mobile","email","phone"],"doctype":"DocField","owner":"Administrator","in_list_view":1,"reqd":1,"ignore_xss_filter":0,"in_global_search":0,"read_only":0,"print_hide":0,"modified_by":"Administrator","ignore_user_permissions":0,"length":0,"label":"Patient","print_hide_if_no_value":0,"allow_bulk_edit":0,"linked_document_type":"Document","set_only_once":0,"docstatus":0,"hidden":0,"in_filter":0,"permlevel":0,"columns":0,"bold":0,"parent":"Vital Signs","search_index":0,"allow_on_submit":0,"precision":"","is_custom_field":null,"remember_last_selected_value":0,"unique":0,"name":"99c96b79dc","idx":1,"in_standard_filter":0,"modified":"2017-09-29 01:32:52.943171","parenttype":"DocType","fieldname":"patient","fieldtype":"Link","options":"Patient","report_hide":0,"parentfield":"fields"},{"collapsible":0,"no_copy":0,"creation":"2017-02-02 11:00:24.853005","search_fields":["patient","physician","appointment_datetime","department"],"doctype":"DocField","owner":"Administrator","in_list_view":0,"reqd":0,"ignore_xss_filter":0,"in_global_search":0,"read_only":1,"print_hide":0,"modified_by":"Administrator","ignore_user_permissions":0,"length":0,"label":"Appointment","print_hide_if_no_value":0,"allow_bulk_edit":0,"linked_document_type":"Document","set_only_once":0,"docstatus":0,"hidden":0,"in_filter":0,"permlevel":0,"columns":0,"bold":0,"parent":"Vital Signs","search_index":0,"allow_on_submit":0,"precision":"","is_custom_field":null,"remember_last_selected_value":0,"unique":0,"name":"99655fc0bf","idx":2,"in_standard_filter":0,"modified":"2017-09-29 01:32:52.943171","parenttype":"DocType","fieldname":"appointment","fieldtype":"Link","options":"Patient Appointment","report_hide":0,"parentfield":"fields"},{"collapsible":0,"no_copy":0,"creation":"2017-02-02 11:00:24.853005","search_fields":["patient","physician","visit_department"],"doctype":"DocField","owner":"Administrator","in_list_view":0,"reqd":0,"ignore_xss_filter":0,"in_global_search":0,"read_only":1,"print_hide":0,"modified_by":"Administrator","ignore_user_permissions":0,"length":0,"label":"Consultation","print_hide_if_no_value":0,"allow_bulk_edit":0,"linked_document_type":"Document","set_only_once":0,"docstatus":0,"hidden":0,"in_filter":0,"permlevel":0,"columns":0,"bold":0,"parent":"Vital Signs","search_index":0,"allow_on_submit":0,"precision":"","is_custom_field":null,"remember_last_selected_value":0,"unique":0,"name":"92427df61f","idx":3,"in_standard_filter":0,"modified":"2017-09-29 01:32:52.943171","parenttype":"DocType","fieldname":"consultation","fieldtype":"Link","options":"Consultation","report_hide":0,"parentfield":"fields"},{"collapsible":0,"no_copy":0,"creation":"2017-02-02 11:00:24.853005","search_fields":null,"doctype":"DocField","owner":"Administrator","in_list_view":0,"reqd":0,"ignore_xss_filter":0,"in_global_search":0,"read_only":0,"print_hide":0,"modified_by":"Administrator","ignore_user_permissions":0,"length":0,"print_hide_if_no_value":0,"allow_bulk_edit":0,"linked_document_type":null,"set_only_once":0,"docstatus":0,"hidden":0,"in_filter":0,"permlevel":0,"columns":0,"bold":0,"parent":"Vital Signs","search_index":0,"allow_on_submit":0,"precision":"","is_custom_field":null,"remember_last_selected_value":0,"unique":0,"name":"ba74669be1","idx":4,"in_standard_filter":0,"modified":"2017-09-29 01:32:52.943171","parenttype":"DocType","fieldname":"column_break_2","fieldtype":"Column Break","report_hide":0,"parentfield":"fields"},{"collapsible":0,"no_copy":0,"creation":"2017-02-02 11:00:24.853005","search_fields":null,"doctype":"DocField","owner":"Administrator","in_list_view":0,"reqd":1,"ignore_xss_filter":0,"in_global_search":0,"read_only":0,"print_hide":0,"modified_by":"Administrator","ignore_user_permissions":0,"length":0,"label":"Date","print_hide_if_no_value":0,"allow_bulk_edit":0,"linked_document_type":null,"set_only_once":0,"docstatus":0,"hidden":0,"in_filter":0,"permlevel":0,"columns":0,"bold":0,"parent":"Vital Signs","search_index":0,"allow_on_submit":0,"precision":"","is_custom_field":null,"remember_last_selected_value":0,"unique":0,"name":"9612d2c929","idx":5,"default":"Today","in_standard_filter":0,"modified":"2017-09-29 01:32:52.943171","parenttype":"DocType","fieldname":"signs_date","fieldtype":"Date","report_hide":0,"parentfield":"fields"},{"collapsible":0,"no_copy":0,"creation":"2017-02-02 11:00:24.853005","search_fields":null,"doctype":"DocField","owner":"Administrator","in_list_view":0,"reqd":0,"ignore_xss_filter":0,"in_global_search":0,"read_only":0,"print_hide":0,"modified_by":"Administrator","ignore_user_permissions":0,"length":0,"print_hide_if_no_value":0,"allow_bulk_edit":0,"linked_document_type":null,"set_only_once":0,"docstatus":0,"hidden":0,"in_filter":0,"permlevel":0,"columns":0,"bold":0,"parent":"Vital Signs","search_index":0,"allow_on_submit":0,"precision":"","is_custom_field":null,"remember_last_selected_value":0,"unique":0,"name":"856f7e4fde","idx":6,"in_standard_filter":0,"modified":"2017-09-29 01:32:52.943171","parenttype":"DocType","fieldname":"column_break_4","fieldtype":"Column Break","report_hide":0,"parentfield":"fields"},{"collapsible":0,"no_copy":0,"creation":"2017-02-02 11:00:24.853005","search_fields":null,"doctype":"DocField","owner":"Administrator","in_list_view":0,"reqd":1,"ignore_xss_filter":0,"in_global_search":0,"read_only":0,"print_hide":0,"modified_by":"Administrator","ignore_user_permissions":0,"length":0,"label":"Time","print_hide_if_no_value":0,"allow_bulk_edit":0,"linked_document_type":null,"set_only_once":0,"docstatus":0,"hidden":0,"in_filter":0,"permlevel":0,"columns":0,"bold":0,"parent":"Vital Signs","search_index":0,"allow_on_submit":0,"precision":"","is_custom_field":null,"remember_last_selected_value":0,"unique":0,"name":"2847892e72","idx":7,"default":"","in_standard_filter":0,"modified":"2017-09-29 01:32:52.943171","parenttype":"DocType","fieldname":"signs_time","fieldtype":"Time","report_hide":0,"parentfield":"fields"},{"collapsible":0,"no_copy":0,"creation":"2017-02-02 11:00:24.853005","search_fields":null,"doctype":"DocField","owner":"Administrator","in_list_view":0,"reqd":0,"ignore_xss_filter":0,"in_global_search":0,"read_only":0,"print_hide":0,"modified_by":"Administrator","ignore_user_permissions":0,"length":0,"label":"Vital Signs","print_hide_if_no_value":0,"allow_bulk_edit":0,"linked_document_type":null,"set_only_once":0,"docstatus":0,"hidden":0,"in_filter":0,"permlevel":0,"columns":0,"bold":0,"parent":"Vital Signs","search_index":0,"allow_on_submit":0,"precision":"","is_custom_field":null,"remember_last_selected_value":0,"unique":0,"name":"f4c148741b","idx":8,"in_standard_filter":0,"modified":"2017-09-29 01:32:52.943171","parenttype":"DocType","fieldname":"sb_vs","fieldtype":"Section Break","report_hide":0,"parentfield":"fields"},{"collapsible":0,"no_copy":0,"creation":"2017-02-02 11:00:24.853005","search_fields":null,"doctype":"DocField","owner":"Administrator","in_list_view":1,"reqd":0,"ignore_xss_filter":0,"in_global_search":0,"description":"Presence of a fever (temp &gt; 38.5 \u00b0C/101.3 \u00b0F or sustained temp &gt; 38 \u00b0C/100.4 \u00b0F)","read_only":0,"print_hide":0,"modified_by":"Administrator","ignore_user_permissions":0,"length":0,"label":"Body Temperature","print_hide_if_no_value":0,"allow_bulk_edit":0,"linked_document_type":null,"set_only_once":0,"docstatus":0,"hidden":0,"in_filter":0,"permlevel":0,"columns":0,"bold":0,"parent":"Vital Signs","search_index":0,"allow_on_submit":0,"precision":"","is_custom_field":null,"remember_last_selected_value":0,"unique":0,"name":"aee17d258a","idx":9,"in_standard_filter":0,"modified":"2017-09-29 01:32:52.943171","parenttype":"DocType","fieldname":"temperature","fieldtype":"Data","report_hide":0,"parentfield":"fields"},{"collapsible":0,"no_copy":0,"creation":"2017-02-02 11:00:24.853005","search_fields":null,"doctype":"DocField","owner":"Administrator","in_list_view":1,"reqd":0,"ignore_xss_filter":0,"in_global_search":0,"description":"Adults' pulse rate is anywhere between 50 and 80 beats per minute.","read_only":0,"print_hide":0,"modified_by":"Administrator","ignore_user_permissions":0,"length":0,"label":"Heart Rate / Pulse","print_hide_if_no_value":0,"allow_bulk_edit":0,"linked_document_type":null,"set_only_once":0,"docstatus":0,"hidden":0,"in_filter":0,"permlevel":0,"columns":0,"bold":0,"parent":"Vital Signs","search_index":0,"allow_on_submit":0,"precision":"","is_custom_field":null,"remember_last_selected_value":0,"unique":0,"name":"b3bef3fab4","idx":10,"in_standard_filter":0,"modified":"2017-09-29 01:32:52.943171","parenttype":"DocType","fieldname":"pulse","fieldtype":"Data","report_hide":0,"parentfield":"fields"},{"collapsible":0,"no_copy":0,"creation":"2017-02-02 11:00:24.853005","search_fields":null,"doctype":"DocField","owner":"Administrator","in_list_view":1,"reqd":0,"ignore_xss_filter":0,"in_global_search":0,"description":"Normal reference range for an adult is 16\u201320 breaths/minute (RCP 2012)","read_only":0,"print_hide":0,"modified_by":"Administrator","ignore_user_permissions":0,"length":0,"label":"Respiratory rate","print_hide_if_no_value":0,"allow_bulk_edit":0,"linked_document_type":null,"set_only_once":0,"docstatus":0,"hidden":0,"in_filter":0,"permlevel":0,"columns":0,"bold":0,"parent":"Vital Signs","search_index":0,"allow_on_submit":0,"precision":"","is_custom_field":null,"remember_last_selected_value":0,"unique":0,"name":"22a9ccfa1d","idx":11,"in_standard_filter":0,"modified":"2017-09-29 01:32:52.943171","parenttype":"DocType","fieldname":"respiratory_rate","fieldtype":"Data","report_hide":0,"parentfield":"fields"},{"collapsible":0,"no_copy":0,"creation":"2017-02-02 11:00:24.853005","search_fields":null,"doctype":"DocField","owner":"Administrator","in_list_view":0,"reqd":0,"ignore_xss_filter":0,"in_global_search":0,"read_only":0,"print_hide":0,"modified_by":"Administrator","ignore_user_permissions":0,"length":0,"print_hide_if_no_value":0,"allow_bulk_edit":0,"linked_document_type":null,"set_only_once":0,"docstatus":0,"hidden":0,"in_filter":0,"permlevel":0,"columns":0,"bold":0,"parent":"Vital Signs","search_index":0,"allow_on_submit":0,"precision":"","is_custom_field":null,"remember_last_selected_value":0,"unique":0,"name":"44d3614f07","idx":12,"in_standard_filter":0,"modified":"2017-09-29 01:32:52.943171","parenttype":"DocType","fieldname":"column_break_8","fieldtype":"Column Break","report_hide":0,"parentfield":"fields"},{"collapsible":0,"no_copy":0,"creation":"2017-02-02 11:00:24.853005","search_fields":null,"doctype":"DocField","owner":"Administrator","in_list_view":1,"reqd":0,"ignore_xss_filter":0,"in_global_search":0,"read_only":0,"print_hide":0,"modified_by":"Administrator","ignore_user_permissions":0,"length":0,"label":"Blood Pressure (systolic)","print_hide_if_no_value":0,"allow_bulk_edit":0,"linked_document_type":null,"set_only_once":0,"docstatus":0,"hidden":0,"in_filter":0,"permlevel":0,"columns":0,"bold":0,"parent":"Vital Signs","search_index":0,"allow_on_submit":0,"precision":"","is_custom_field":null,"remember_last_selected_value":0,"unique":0,"name":"d11799fb45","idx":13,"in_standard_filter":0,"modified":"2017-09-29 01:32:52.943171","parenttype":"DocType","fieldname":"bp_systolic","fieldtype":"Data","report_hide":0,"parentfield":"fields"},{"collapsible":0,"no_copy":0,"creation":"2017-02-02 11:00:24.853005","search_fields":null,"doctype":"DocField","owner":"Administrator","in_list_view":1,"reqd":0,"ignore_xss_filter":0,"in_global_search":0,"description":"","read_only":0,"print_hide":0,"modified_by":"Administrator","ignore_user_permissions":0,"length":0,"label":"Blood Pressure (diastolic)","print_hide_if_no_value":0,"allow_bulk_edit":0,"linked_document_type":null,"set_only_once":0,"docstatus":0,"hidden":0,"in_filter":0,"permlevel":0,"columns":0,"bold":0,"parent":"Vital Signs","search_index":0,"allow_on_submit":0,"precision":"","is_custom_field":null,"remember_last_selected_value":0,"unique":0,"name":"18cb6b65e0","idx":14,"in_standard_filter":0,"modified":"2017-09-29 01:32:52.943171","parenttype":"DocType","fieldname":"bp_diastolic","fieldtype":"Data","report_hide":0,"parentfield":"fields"},{"collapsible":0,"no_copy":0,"creation":"2017-02-02 11:00:24.853005","search_fields":null,"doctype":"DocField","owner":"Administrator","in_list_view":0,"reqd":0,"ignore_xss_filter":0,"in_global_search":0,"description":"Normal resting blood pressure in an adult is approximately 120 mmHg systolic, and 80 mmHg diastolic, abbreviated \"120/80 mmHg\"","read_only":1,"print_hide":0,"modified_by":"Administrator","ignore_user_permissions":0,"length":0,"label":"Blood Pressure","print_hide_if_no_value":0,"allow_bulk_edit":0,"linked_document_type":null,"set_only_once":0,"docstatus":0,"hidden":0,"in_filter":0,"permlevel":0,"columns":0,"bold":0,"parent":"Vital Signs","search_index":0,"allow_on_submit":0,"precision":"","is_custom_field":null,"remember_last_selected_value":0,"unique":0,"name":"c713027f91","idx":15,"in_standard_filter":0,"modified":"2017-09-29 01:32:52.943171","parenttype":"DocType","fieldname":"bp","fieldtype":"Data","report_hide":0,"parentfield":"fields"},{"collapsible":0,"no_copy":0,"creation":"2017-02-02 11:00:24.853005","search_fields":null,"doctype":"DocField","owner":"Administrator","in_list_view":0,"reqd":0,"ignore_xss_filter":0,"in_global_search":0,"read_only":0,"print_hide":0,"modified_by":"Administrator","ignore_user_permissions":0,"length":0,"label":"Notes","print_hide_if_no_value":0,"allow_bulk_edit":0,"linked_document_type":null,"set_only_once":0,"docstatus":0,"hidden":0,"in_filter":0,"permlevel":0,"columns":0,"bold":0,"parent":"Vital Signs","search_index":0,"allow_on_submit":0,"precision":"","is_custom_field":null,"remember_last_selected_value":0,"unique":0,"name":"93a40a0758","idx":16,"in_standard_filter":0,"modified":"2017-09-29 01:32:52.943171","parenttype":"DocType","fieldname":"vital_signs_note","fieldtype":"Small Text","report_hide":0,"parentfield":"fields"},{"collapsible":0,"no_copy":0,"creation":"2017-02-02 11:00:24.853005","search_fields":null,"doctype":"DocField","owner":"Administrator","in_list_view":0,"reqd":0,"ignore_xss_filter":0,"in_global_search":0,"read_only":0,"print_hide":0,"modified_by":"Administrator","ignore_user_permissions":0,"length":0,"label":"Nutrition Values","print_hide_if_no_value":0,"allow_bulk_edit":0,"linked_document_type":null,"set_only_once":0,"docstatus":0,"hidden":0,"in_filter":0,"permlevel":0,"columns":0,"bold":0,"parent":"Vital Signs","search_index":0,"allow_on_submit":0,"precision":"","is_custom_field":null,"remember_last_selected_value":0,"unique":0,"name":"fc4c46d643","idx":17,"in_standard_filter":0,"modified":"2017-09-29 01:32:52.943171","parenttype":"DocType","fieldname":"sb_nutrition_values","fieldtype":"Section Break","report_hide":0,"parentfield":"fields"},{"collapsible":0,"no_copy":0,"creation":"2017-02-02 11:00:24.853005","search_fields":null,"doctype":"DocField","owner":"Administrator","in_list_view":1,"reqd":0,"ignore_xss_filter":0,"in_global_search":0,"read_only":0,"print_hide":0,"modified_by":"Administrator","ignore_user_permissions":0,"length":0,"label":"Height (In Meter)","print_hide_if_no_value":0,"allow_bulk_edit":0,"linked_document_type":null,"set_only_once":0,"docstatus":0,"hidden":0,"in_filter":0,"permlevel":0,"columns":0,"bold":0,"parent":"Vital Signs","search_index":0,"allow_on_submit":0,"precision":"","is_custom_field":null,"remember_last_selected_value":0,"unique":0,"name":"8d5698ddc9","idx":18,"in_standard_filter":0,"modified":"2017-09-29 01:32:52.943171","parenttype":"DocType","fieldname":"height","fieldtype":"Float","report_hide":0,"parentfield":"fields"},{"collapsible":0,"no_copy":0,"creation":"2017-02-02 11:00:24.853005","search_fields":null,"doctype":"DocField","owner":"Administrator","in_list_view":1,"reqd":0,"ignore_xss_filter":0,"in_global_search":0,"read_only":0,"print_hide":0,"modified_by":"Administrator","ignore_user_permissions":0,"length":0,"label":"Weight (In Kilogram)","print_hide_if_no_value":0,"allow_bulk_edit":0,"linked_document_type":null,"set_only_once":0,"docstatus":0,"hidden":0,"in_filter":0,"permlevel":0,"columns":0,"bold":0,"parent":"Vital Signs","search_index":0,"allow_on_submit":0,"precision":"","is_custom_field":null,"remember_last_selected_value":0,"unique":0,"name":"4fd3b0f258","idx":19,"in_standard_filter":0,"modified":"2017-09-29 01:32:52.943171","parenttype":"DocType","fieldname":"weight","fieldtype":"Float","report_hide":0,"parentfield":"fields"},{"collapsible":0,"no_copy":0,"creation":"2017-02-02 11:00:24.853005","search_fields":null,"doctype":"DocField","owner":"Administrator","in_list_view":1,"reqd":0,"ignore_xss_filter":0,"in_global_search":0,"read_only":1,"print_hide":0,"modified_by":"Administrator","ignore_user_permissions":0,"length":0,"label":"BMI","print_hide_if_no_value":0,"allow_bulk_edit":0,"linked_document_type":null,"set_only_once":0,"docstatus":0,"hidden":0,"in_filter":0,"permlevel":0,"columns":0,"bold":0,"parent":"Vital Signs","search_index":0,"allow_on_submit":0,"precision":"","is_custom_field":null,"remember_last_selected_value":0,"unique":0,"name":"95e7feda7e","idx":20,"default":"0.00","in_standard_filter":0,"modified":"2017-09-29 01:32:52.943171","parenttype":"DocType","fieldname":"bmi","fieldtype":"Float","report_hide":0,"parentfield":"fields"},{"collapsible":0,"no_copy":0,"creation":"2017-02-02 11:00:24.853005","search_fields":null,"doctype":"DocField","owner":"Administrator","in_list_view":0,"reqd":0,"ignore_xss_filter":0,"in_global_search":0,"read_only":0,"print_hide":0,"modified_by":"Administrator","ignore_user_permissions":0,"length":0,"print_hide_if_no_value":0,"allow_bulk_edit":0,"linked_document_type":null,"set_only_once":0,"docstatus":0,"hidden":0,"in_filter":0,"permlevel":0,"columns":0,"bold":0,"parent":"Vital Signs","search_index":0,"allow_on_submit":0,"precision":"","is_custom_field":null,"remember_last_selected_value":0,"unique":0,"name":"de3070ca2b","idx":21,"in_standard_filter":0,"modified":"2017-09-29 01:32:52.943171","parenttype":"DocType","fieldname":"column_break_14","fieldtype":"Column Break","report_hide":0,"parentfield":"fields"},{"collapsible":0,"no_copy":0,"creation":"2017-02-02 11:00:24.853005","search_fields":null,"doctype":"DocField","owner":"Administrator","in_list_view":0,"reqd":0,"ignore_xss_filter":0,"in_global_search":0,"read_only":0,"print_hide":0,"modified_by":"Administrator","ignore_user_permissions":0,"length":0,"label":"Notes","print_hide_if_no_value":0,"allow_bulk_edit":0,"linked_document_type":null,"set_only_once":0,"docstatus":0,"hidden":0,"in_filter":0,"permlevel":0,"columns":0,"bold":0,"parent":"Vital Signs","search_index":0,"allow_on_submit":0,"precision":"","is_custom_field":null,"remember_last_selected_value":0,"unique":0,"name":"2328565a57","idx":22,"in_standard_filter":0,"modified":"2017-09-29 01:32:52.943171","parenttype":"DocType","fieldname":"nutrition_note","fieldtype":"Small Text","report_hide":0,"parentfield":"fields"},{"collapsible":0,"no_copy":0,"creation":"2017-02-02 11:00:24.853005","search_fields":null,"doctype":"DocField","owner":"Administrator","in_list_view":0,"reqd":0,"ignore_xss_filter":0,"in_global_search":0,"read_only":0,"print_hide":0,"modified_by":"Administrator","ignore_user_permissions":0,"length":0,"label":"Company","print_hide_if_no_value":0,"allow_bulk_edit":0,"linked_document_type":"Setup","set_only_once":0,"docstatus":0,"hidden":1,"in_filter":0,"permlevel":0,"columns":0,"bold":0,"parent":"Vital Signs","search_index":0,"allow_on_submit":0,"precision":"","is_custom_field":null,"remember_last_selected_value":0,"unique":0,"name":"b94748a87b","idx":23,"in_standard_filter":0,"modified":"2017-09-29 01:32:52.943171","parenttype":"DocType","fieldname":"company","fieldtype":"Link","options":"Company","report_hide":0,"parentfield":"fields"},{"collapsible":0,"no_copy":1,"creation":"2017-02-02 11:00:24.853005","search_fields":["patient","signs_date"],"doctype":"DocField","owner":"Administrator","in_list_view":0,"reqd":0,"ignore_xss_filter":0,"in_global_search":0,"read_only":1,"print_hide":1,"modified_by":"Administrator","ignore_user_permissions":0,"length":0,"label":"Amended From","print_hide_if_no_value":0,"allow_bulk_edit":0,"linked_document_type":"","set_only_once":0,"docstatus":0,"hidden":0,"in_filter":0,"permlevel":0,"columns":0,"bold":0,"parent":"Vital Signs","search_index":0,"allow_on_submit":0,"is_custom_field":null,"remember_last_selected_value":0,"unique":0,"name":"10b0a6594c","idx":24,"in_standard_filter":0,"modified":"2017-09-29 01:32:52.943171","parenttype":"DocType","fieldname":"amended_from","fieldtype":"Link","options":"Vital Signs","report_hide":0,"parentfield":"fields"}],"image_view":0,"allow_import":1,"creation":"2017-02-02 11:00:24.853005","search_fields":"patient, signs_date","track_changes":1,"track_seen":1,"sort_order":"DESC","__linked_with":null,"owner":"Administrator","editable_grid":1,"__form_grid_templates":null,"in_create":0,"read_only":0,"__templates":null,"document_type":"","hide_heading":0,"modified_by":"Administrator","allow_rename":0,"__kanban_column_fields":[],"custom":0,"max_attachments":0,"__js":"\n\n/* Adding /home/frappe/frappe-bench/apps/erpnext/erpnext/healthcare/doctype/vital_signs/vital_signs.js */\n\n// Copyright (c) 2016, ESS LLP and contributors\n// For license information, please see license.txt\n\nfrappe.ui.form.on(\"Vital Signs\", \"height\", function(frm) {\n\tif(frm.doc.height && frm.doc.weight){\n\t\tcalculate_bmi(frm);\n\t}\n});\n\nfrappe.ui.form.on(\"Vital Signs\", \"weight\", function(frm) {\n\tif(frm.doc.height && frm.doc.weight){\n\t\tcalculate_bmi(frm);\n\t}\n});\n\nvar calculate_bmi = function(frm){\n\t// Reference https://en.wikipedia.org/wiki/Body_mass_index\n\t// bmi = weight (in Kg) / height * height (in Meter)\n\tvar bmi = (frm.doc.weight/(frm.doc.height*frm.doc.height)).toFixed(2);\n\tvar bmi_note = null;\n\tif(bmi<18.5){\n\t\tbmi_note = \"Underweight\";\n\t}else if(bmi>=18.5 && bmi<25){\n\t\tbmi_note = \"Normal\";\n\t}else if(bmi>=25 && bmi<30){\n\t\tbmi_note = \"Overweight\";\n\t}else if(bmi>=30){\n\t\tbmi_note = \"Obese\";\n\t}\n\tfrappe.model.set_value(frm.doctype,frm.docname, \"bmi\", bmi);\n\tfrappe.model.set_value(frm.doctype,frm.docname, \"nutrition_note\", bmi_note);\n};\n\nfrappe.ui.form.on(\"Vital Signs\", \"bp_systolic\", function(frm) {\n\tif(frm.doc.bp_systolic && frm.doc.bp_diastolic){\n\t\tset_bp(frm);\n\t}\n});\n\nfrappe.ui.form.on(\"Vital Signs\", \"bp_diastolic\", function(frm) {\n\tif(frm.doc.bp_systolic && frm.doc.bp_diastolic){\n\t\tset_bp(frm);\n\t}\n});\n\nvar set_bp = function(frm){\n\tvar bp = frm.doc.bp_systolic+\"/\"+frm.doc.bp_diastolic+\" mmHg\";\n\tfrappe.model.set_value(frm.doctype,frm.docname, \"bp\", bp);\n};\n","__tree_js":null,"docstatus":0,"sort_field":"modified","__messages":null,"allow_copy":1,"engine":"InnoDB","allow_guest_to_view":0,"istable":0,"has_web_view":0,"__map_js":null,"__css":null,"show_name_in_global_search":1,"beta":1,"read_only_onload":0,"module":"Healthcare","doctype":"DocType","__dashboard":{},"__kanban_boards":[],"issingle":0,"__listview_template":null,"name":"Vital Signs","idx":0,"hide_toolbar":0,"__workflow_docs":[],"title_field":"patient","modified":"2017-09-04 14:31:57.851546","is_submittable":1,"name_case":"","__calendar_js":null,"restrict_to_domain":"Healthcare","__list_js":null,"permissions":[{"creation":"2017-02-02 11:00:24.853005","share":1,"doctype":"DocPerm","owner":"Administrator","export":1,"cancel":1,"set_user_permissions":0,"modified_by":"Administrator","create":1,"submit":1,"write":1,"role":"Physician","print":1,"docstatus":0,"permlevel":0,"parent":"Vital Signs","read":1,"import":0,"report":1,"apply_user_permissions":0,"name":"7a26013bad","idx":1,"amend":0,"modified":"2017-09-29 01:32:52.943171","email":1,"parenttype":"DocType","parentfield":"permissions","if_owner":0,"delete":1},{"creation":"2017-02-02 11:00:24.853005","share":1,"doctype":"DocPerm","owner":"Administrator","export":1,"cancel":1,"set_user_permissions":0,"modified_by":"Administrator","create":1,"submit":1,"write":1,"role":"Nursing User","print":1,"docstatus":0,"permlevel":0,"parent":"Vital Signs","read":1,"import":0,"report":1,"apply_user_permissions":0,"name":"dff34597fe","idx":2,"amend":0,"modified":"2017-09-29 01:32:52.943171","email":1,"parenttype":"DocType","parentfield":"permissions","if_owner":0,"delete":1}],"quick_entry":0,"__custom_js":"","__print_formats":[]}],"user_settings":"{}"}