{"docs":[{"fields":[{"collapsible":0,"no_copy":0,"creation":"2014-06-19 05:20:26.331041","search_fields":null,"doctype":"DocField","owner":"Administrator","in_list_view":1,"reqd":1,"ignore_xss_filter":0,"in_global_search":0,"read_only":0,"print_hide":0,"modified_by":"Administrator","ignore_user_permissions":0,"length":0,"label":"Subject","print_hide_if_no_value":0,"allow_bulk_edit":0,"linked_document_type":null,"set_only_once":0,"docstatus":0,"hidden":0,"in_filter":0,"permlevel":0,"columns":0,"bold":0,"parent":"Standard Reply","search_index":0,"allow_on_submit":0,"is_custom_field":null,"remember_last_selected_value":0,"unique":0,"name":"a2aa9b38bb","idx":1,"in_standard_filter":0,"modified":"2017-06-09 23:47:41.731800","parenttype":"DocType","fieldname":"subject","fieldtype":"Data","report_hide":0,"parentfield":"fields"},{"collapsible":0,"no_copy":0,"creation":"2014-06-19 05:20:26.331041","search_fields":null,"doctype":"DocField","owner":"Administrator","in_list_view":1,"reqd":1,"ignore_xss_filter":0,"in_global_search":0,"read_only":0,"print_hide":0,"modified_by":"Administrator","ignore_user_permissions":0,"length":0,"label":"Response","print_hide_if_no_value":0,"allow_bulk_edit":0,"linked_document_type":null,"set_only_once":0,"docstatus":0,"hidden":0,"in_filter":0,"permlevel":0,"columns":0,"bold":0,"parent":"Standard Reply","search_index":0,"allow_on_submit":0,"is_custom_field":null,"remember_last_selected_value":0,"unique":0,"name":"83fe879740","idx":2,"in_standard_filter":0,"modified":"2017-06-09 23:47:41.731800","parenttype":"DocType","fieldname":"response","fieldtype":"Text Editor","report_hide":0,"parentfield":"fields"},{"collapsible":0,"no_copy":0,"creation":"2014-06-19 05:20:26.331041","search_fields":["full_name"],"doctype":"DocField","owner":"Administrator","in_list_view":0,"reqd":0,"ignore_xss_filter":0,"in_global_search":0,"read_only":0,"print_hide":0,"modified_by":"Administrator","ignore_user_permissions":0,"length":0,"label":"Owner","print_hide_if_no_value":0,"allow_bulk_edit":0,"linked_document_type":"","set_only_once":0,"docstatus":0,"hidden":1,"in_filter":0,"permlevel":0,"columns":0,"bold":0,"parent":"Standard Reply","search_index":0,"allow_on_submit":0,"is_custom_field":null,"remember_last_selected_value":0,"unique":0,"name":"9c8072b85d","idx":3,"default":"user","in_standard_filter":0,"modified":"2017-06-09 23:47:41.731800","parenttype":"DocType","fieldname":"owner","fieldtype":"Link","options":"User","report_hide":0,"parentfield":"fields"},{"collapsible":0,"no_copy":0,"creation":"2014-06-19 05:20:26.331041","search_fields":null,"doctype":"DocField","owner":"Administrator","in_list_view":0,"reqd":0,"ignore_xss_filter":0,"in_global_search":0,"read_only":0,"print_hide":0,"modified_by":"Administrator","ignore_user_permissions":0,"length":0,"print_hide_if_no_value":0,"allow_bulk_edit":0,"linked_document_type":null,"set_only_once":0,"docstatus":0,"hidden":0,"in_filter":0,"permlevel":0,"columns":0,"bold":0,"parent":"Standard Reply","search_index":0,"allow_on_submit":0,"precision":"","is_custom_field":null,"remember_last_selected_value":0,"unique":0,"name":"051eee3ab5","idx":4,"in_standard_filter":0,"modified":"2017-06-09 23:47:41.731800","parenttype":"DocType","fieldname":"section_break_4","fieldtype":"Section Break","report_hide":0,"parentfield":"fields"},{"collapsible":0,"no_copy":0,"creation":"2014-06-19 05:20:26.331041","search_fields":null,"doctype":"DocField","owner":"Administrator","in_list_view":0,"reqd":0,"ignore_xss_filter":0,"in_global_search":0,"read_only":0,"print_hide":0,"modified_by":"Administrator","ignore_user_permissions":0,"length":0,"label":"Standard Reply Help","print_hide_if_no_value":0,"allow_bulk_edit":0,"linked_document_type":null,"set_only_once":0,"docstatus":0,"hidden":0,"in_filter":0,"permlevel":0,"columns":0,"bold":0,"parent":"Standard Reply","search_index":0,"allow_on_submit":0,"precision":"","is_custom_field":null,"remember_last_selected_value":0,"unique":0,"name":"cb80821daf","idx":5,"in_standard_filter":0,"modified":"2017-06-09 23:47:41.731800","parenttype":"DocType","fieldname":"standard_reply_help","fieldtype":"HTML","options":"<h4>Standard Reply Example</h4>\n\n<pre>Order Overdue\n\nTransaction {{ name }} has exceeded Due Date. Please take necessary action.\n\nDetails\n\n- Customer: {{ customer }}\n- Amount: {{ grand_total }}\n</pre>\n\n<h4>How to get fieldnames</h4>\n\n<p>The fieldnames you can use in your standard reply are the fields in the document from which you are sending the email. You can find out the fields of any documents via Setup &gt; Customize Form View and selecting the document type (e.g. Sales Invoice)</p>\n\n<h4>Templating</h4>\n\n<p>Templates are compiled using the Jinja Templating Langauge. To learn more about Jinja, <a class=\"strong\" href=\"http://jinja.pocoo.org/docs/dev/templates/\">read this documentation.</a></p>\n","report_hide":0,"parentfield":"fields"}],"image_view":0,"allow_import":1,"creation":"2014-06-19 05:20:26.331041","__list_js":null,"track_changes":1,"track_seen":0,"sort_order":"DESC","__linked_with":null,"__dashboard":{},"owner":"Administrator","editable_grid":0,"__form_grid_templates":null,"in_create":0,"read_only":0,"__templates":null,"document_type":"Document","hide_heading":0,"modified_by":"Administrator","allow_rename":1,"__kanban_column_fields":[],"custom":0,"max_attachments":0,"__js":"\n\n/* Adding /home/frappe/frappe-bench/apps/frappe/frappe/email/doctype/standard_reply/standard_reply.js */\n\n// Copyright (c) 2016, Frappe Technologies and contributors\n// For license information, please see license.txt\n\nfrappe.ui.form.on('Standard Reply', {\n\trefresh: function(frm) {\n\n\t}\n});\n","__tree_js":null,"docstatus":0,"sort_field":"modified","__messages":null,"allow_copy":0,"engine":"InnoDB","allow_guest_to_view":0,"istable":0,"has_web_view":0,"__map_js":null,"__css":null,"show_name_in_global_search":0,"beta":0,"read_only_onload":0,"module":"Email","doctype":"DocType","autoname":"field:subject","__kanban_boards":[],"issingle":0,"icon":"fa fa-comment","__listview_template":null,"name":"Standard Reply","idx":0,"hide_toolbar":0,"__workflow_docs":[],"modified":"2016-12-29 14:40:02.827994","is_submittable":0,"name_case":"","__calendar_js":null,"permissions":[{"creation":"2014-06-19 05:20:26.331041","share":1,"doctype":"DocPerm","owner":"Administrator","export":0,"cancel":0,"set_user_permissions":0,"modified_by":"Administrator","create":1,"submit":0,"write":1,"role":"All","print":0,"docstatus":0,"permlevel":0,"parent":"Standard Reply","read":1,"import":0,"report":0,"apply_user_permissions":0,"name":"a68f1bae0b","idx":1,"amend":0,"modified":"2017-06-09 23:47:41.731800","email":0,"parenttype":"DocType","parentfield":"permissions","if_owner":0,"delete":0},{"creation":"2014-06-19 05:20:26.331041","share":1,"doctype":"DocPerm","owner":"Administrator","export":1,"cancel":0,"set_user_permissions":0,"modified_by":"Administrator","create":1,"submit":0,"write":1,"role":"System Manager","print":0,"docstatus":0,"permlevel":0,"parent":"Standard Reply","read":1,"import":1,"report":1,"apply_user_permissions":0,"name":"f61fa8f1f9","idx":2,"amend":0,"modified":"2017-06-09 23:47:41.731800","email":1,"parenttype":"DocType","parentfield":"permissions","if_owner":0,"delete":1}],"quick_entry":0,"__custom_js":"","__print_formats":[]}],"user_settings":"{}"}